main.py
redirect_chain-0.2.1.dist-info/LICENSE
redirect_chain-0.2.1.dist-info/LICENSE~
redirect_chain-0.2.1.dist-info/METADATA
redirect_chain-0.2.1.dist-info/WHEEL
redirect_chain-0.2.1.dist-info/entry_points.txt
redirect_chain-0.2.1.dist-info/top_level.txt
redirect_chain-0.2.1.dist-info/RECORD
