Metadata-Version: 2.1
Name: redirect-chain
Version: 0.2.1
Summary: Shows the redirect chain of a URL from start to end
Home-page: https://github.com/peterbe/redirect-chain
Author: Peter Bengtsson
Author-email: mail@peterbe.com
License: MIT
Platform: UNKNOWN
Classifier: Intended Audience :: Developers
Classifier: Intended Audience :: System Administrators
Classifier: License :: OSI Approved :: MIT License
Classifier: Programming Language :: Python :: 3
Requires-Python: >=3.5
Requires-Dist: requests
